bayesian_mpn_calculator/__init__.py
bayesian_mpn_calculator/mpn_calculator.py
bayesian_mpn_calculator-0.1.0.dist-info/LICENSE
bayesian_mpn_calculator-0.1.0.dist-info/METADATA
bayesian_mpn_calculator-0.1.0.dist-info/WHEEL
bayesian_mpn_calculator-0.1.0.dist-info/entry_points.txt
bayesian_mpn_calculator-0.1.0.dist-info/top_level.txt
bayesian_mpn_calculator-0.1.0.dist-info/RECORD
