Metadata-Version: 2.1
Name: bayesian_mpn_calculator
Version: 0.1.0
Summary: A package to calculate Most Probable Number (MPN) using Bayesian inference.
Home-page: https://github.com/clabe-wekesa/bayesian-mpn-calculator
Author: Clabe Wekesa
Author-email: simiyu86wekesa@gmail.com
License: MIT
Keywords: bayesian inference,MPN,biostatistics,microbiology,pymc
Classifier: License :: OSI Approved :: MIT License
Classifier: Development Status :: 4 - Beta
Classifier: Intended Audience :: Science/Research
Classifier: Programming Language :: Python :: 3.8
Classifier: Programming Language :: Python :: 3.9
Classifier: Programming Language :: Python :: 3.10
Classifier: Programming Language :: Python :: 3.11
Classifier: Operating System :: OS Independent
Requires-Python: >=3.6
License-File: LICENSE
Requires-Dist: Click
Requires-Dist: pymc
Requires-Dist: numpy
Requires-Dist: pandas
Requires-Dist: matplotlib
Requires-Dist: seaborn
